deltacycle/__init__.py
deltacycle/_container.py
deltacycle/_credit_pool.py
deltacycle/_event.py
deltacycle/_kernel.py
deltacycle/_kernel_if.py
deltacycle/_queue.py
deltacycle/_semaphore.py
deltacycle/_task.py
deltacycle/_top.py
deltacycle/_variable.py
deltacycle-0.28.1.dist-info/METADATA
deltacycle-0.28.1.dist-info/WHEEL
deltacycle-0.28.1.dist-info/top_level.txt
deltacycle-0.28.1.dist-info/RECORD
