Metadata-Version: 2.4
Name: deltacycle
Version: 0.28.1
Summary: Delta Cycle
Project-URL: Repository, https://github.com/cjdrake/deltacycle.git
Requires-Python: >=3.12
